deep_ei.py
deep_ei-0.7.0.dist-info/LICENSE
deep_ei-0.7.0.dist-info/METADATA
deep_ei-0.7.0.dist-info/WHEEL
deep_ei-0.7.0.dist-info/top_level.txt
deep_ei-0.7.0.dist-info/RECORD
