Metadata-Version: 2.1
Name: deep-ei
Version: 0.7.0
Summary: Tools for examining the causal structure of artificial neural networks built with PyTorch
Home-page: https://github.com/EI-research-group/deep-ei
Author: Simon Mattsson, Eric J. Michaud, Erik Hoel
Author-email: eric.michaud99@gmail.com
License: MIT
Platform: UNKNOWN
Requires-Dist: torch
Requires-Dist: scikit-learn
Requires-Dist: fast-histogram
Requires-Dist: networkx
